sparc_visualization/__init__.py
sparc_visualization/objects/board.py
sparc_visualization/objects/tile.py
sparc_visualization/plot.py
sparc_visualization/plots/black_frame_plot.py
sparc_visualization/plots/coordinate_grid_plot.py
sparc_visualization/plots/low_contrast_plot.py
sparc_visualization/plots/low_resolution_plot.py
sparc_visualization/plots/original_plot.py
sparc_visualization/plots/path_cell_annotation_plot.py
sparc_visualization/plots/plot.py
sparc_visualization/plots/rotated_plot.py
sparc_visualization/plots/start_end_marked_plot.py
sparc_visualization/plots/text_plot.py
sparc_visualization/prompt.py
sparc_visualization/prompts/default.py
sparc_visualization/prompts/prompt_engineering.py
sparc_visualization/prompts/prompts.py
sparc_visualization/util.py
sparc_visualization-0.1.4.dist-info/METADATA
sparc_visualization-0.1.4.dist-info/WHEEL
sparc_visualization-0.1.4.dist-info/licenses/LICENCE.txt
sparc_visualization-0.1.4.dist-info/RECORD
