Metadata-Version: 2.4
Name: sparc-visualization
Version: 0.1.4
Summary: 
License-Expression: MIT
License-File: LICENCE.txt
Author: Florian Valentin Wunderlich
Author-email: florian.valentin.wunderlich@gmail.com
Requires-Python: >=3.10
Classifier: Programming Language :: Python :: 3
Classifier: Programming Language :: Python :: 3.10
Classifier: Programming Language :: Python :: 3.11
Classifier: Programming Language :: Python :: 3.12
Classifier: Programming Language :: Python :: 3.13
Classifier: Programming Language :: Python :: 3.14
Requires-Dist: Pillow (>=12)
